SpotiStats/__init__.py
SpotiStats/__main__.py
SpotiStats/exceptions.py
SpotiStats/spotify.py
SpotiStats/test.py
SpotiStats-0.1.4.1.dist-info/METADATA
SpotiStats-0.1.4.1.dist-info/WHEEL
SpotiStats-0.1.4.1.dist-info/top_level.txt
SpotiStats-0.1.4.1.dist-info/RECORD
