Metadata-Version: 2.1
Name: SpotiStats
Version: 0.1.4.1
Author-email: jaypyles <jpylesbusiness@gmail.com>
License: MIT
Requires-Python: >=3.9
